<item>
<title>[B]Anime 24Hrs[/B]</title>
<link>https://stmv1.srvif.com/animetv/animetv/playlist.m3u8</link>
<thumbnail>LINK DA IMAGEM QUE FICA NO LADO DO KODI</thumbnail>
<fanart>LINK DO FANART DO CANAL OU DO ADDON QUE FICA NO FUNDO</fanart>
<info>INFO DOS CANAIS.</info>
</item>
<item>
<title>[B]Simpson 24 Hrs[/B]</title>
<link>http://15.235.12.50:2052/24Horas_Simpsons/video.m3u8?token=live_uaywqqpa</link>
<thumbnail>LINK DA IMAGEM QUE FICA NO LADO DO KODI</thumbnail>
<fanart>LINK DO FANART DO CANAL OU DO ADDON QUE FICA NO FUNDO</fanart>
<info>INFO DOS CANAIS.</info>
</item> 
<item>
<title>[B]Pica Pau 24 Hrs[/B]</title>
<link>https://www.youtube.com/watch?v=ryBoWZi-5xk&ab_channel=Pica-PauemPortugu%C3%AAs</link>
<thumbnail>LINK DA IMAGEM QUE FICA NO LADO DO KODI</thumbnail>
<fanart>LINK DO FANART DO CANAL OU DO ADDON QUE FICA NO FUNDO</fanart>
<info>INFO DOS CANAIS.</info>
</item> 
<item>
<title>[B]Peppa Pig 24 Hrs[/B]</title>
<link>https://www.youtube.com/watch?v=6xBFTOVef2M&ab_channel=PeppaPigemPortugu%C3%AAsBrasil-CanalOficial</link>
<thumbnail>LINK DA IMAGEM QUE FICA NO LADO DO KODI</thumbnail>
<fanart>LINK DO FANART DO CANAL OU DO ADDON QUE FICA NO FUNDO</fanart>
<info>INFO DOS CANAIS.</info>
</item> 
<item>
 <item>
<title>[B]Pj Mask 24 Hrs[/B]</title>
<link>https://www.youtube.com/watch?v=abqkFzyGjWc&ab_channel=PJMasksBrasil%E2%80%93CanalOficial</link>
<thumbnail>LINK DA IMAGEM QUE FICA NO LADO DO KODI</thumbnail>
<fanart>LINK DO FANART DO CANAL OU DO ADDON QUE FICA NO FUNDO</fanart>
<info>INFO DOS CANAIS.</info>
</item>
 <item>
<title>[B]Desenhos Cartoon Network 24 Hrs[/B]</title>
<link>https://www.youtube.com/watch?v=hpXd-M9ZDCE&ab_channel=CartoonNetworkBrasil</link>
<thumbnail>LINK DA IMAGEM QUE FICA NO LADO DO KODI</thumbnail>
<fanart>LINK DO FANART DO CANAL OU DO ADDON QUE FICA NO FUNDO</fanart>
<info>INFO DOS CANAIS.</info>
</item>
<item>
<title>[B]Dragon Ball 24 Hrs[/B]</title>
<link>http://dns.ccdns2.xyz:80/live/homevod/ihxOy9YYvoH4bO1qBvf1zuU6m/22487.m3u8</link>
<thumbnail>LINK DA IMAGEM QUE FICA NO LADO DO KODI</thumbnail>
<fanart>LINK DO FANART DO CANAL OU DO ADDON QUE FICA NO FUNDO</fanart>
<info>INFO DOS CANAIS.</info>
</item>
 <item>
<title>[B]Super Shock 24 Hrs[/B]</title>
<link>http://dns.ccdns2.xyz:80/live/homevod/ihxOy9YYvoH4bO1qBvf1zuU6m/36476.m3u8</link>
<thumbnail>LINK DA IMAGEM QUE FICA NO LADO DO KODI</thumbnail>
<fanart>LINK DO FANART DO CANAL OU DO ADDON QUE FICA NO FUNDO</fanart>
<info>INFO DOS CANAIS.</info>
</item>
 <item>
<title>[B]Bob Esponja 24 Hrs[/B]</title>
<link>http://dns.ccdns2.xyz:80/live/homevod/ihxOy9YYvoH4bO1qBvf1zuU6m/13269.m3u8</link>
<thumbnail>LINK DA IMAGEM QUE FICA NO LADO DO KODI</thumbnail>
<fanart>LINK DO FANART DO CANAL OU DO ADDON QUE FICA NO FUNDO</fanart>
<info>INFO DOS CANAIS.</info>
</item>
  <item>
<title>[B]Todo Mundo Odeia O Cris 24 Hrs[/B]</title>
<link>http://dns.ccdns2.xyz:80/live/homevod/ihxOy9YYvoH4bO1qBvf1zuU6m/9659.m3u8</link>
<thumbnail>LINK DA IMAGEM QUE FICA NO LADO DO KODI</thumbnail>
<fanart>LINK DO FANART DO CANAL OU DO ADDON QUE FICA NO FUNDO</fanart>
<info>INFO DOS CANAIS.</info>
</item>
  <item>
<title>[B]Coragem O Cão Covarde 24 Hrs[/B]</title>
<link>http://dns.ccdns2.xyz:80/live/homevod/ihxOy9YYvoH4bO1qBvf1zuU6m/20254.m3u8</link>
<thumbnail>LINK DA IMAGEM QUE FICA NO LADO DO KODI</thumbnail>
<fanart>LINK DO FANART DO CANAL OU DO ADDON QUE FICA NO FUNDO</fanart>
<info>INFO DOS CANAIS.</info>
</item>
<item>
<title>[B]Filmes Antigos[/B]</title>
<link>https://59f2354c05961.streamlock.net:1443/rbtv/_definst_/rbtv/chunklist_w700286621.m3u8</link>
<thumbnail>LINK DA IMAGEM QUE FICA NO LADO DO KODI</thumbnail>
<fanart>LINK DO FANART DO CANAL OU DO ADDON QUE FICA NO FUNDO</fanart>
<info>INFO DOS CANAIS.</info>
</item>
