<item>
<title>[B]|||| [COLOR gold]Eventos Dia 08/09/22[/COLOR] ||||[/B]</title> 
<link>here</link>
<thumbnail>https://i.imgur.com/Bs9javZ.png</thumbnail>
<fanart>https://i.imgur.com/Bs9javZ.png</fanart>
<info>Enventos Esportivos Acontecidos no Dia 08/09/22</info>
</item>

<item>
<title>[B]São Paulo [COLOR gold]x[/COLOR] Atlético-GO FHD[/B]</title>
<link>  </link>
<thumbnail>https://esportenewsmundo.com.br/wp-content/uploads/2022/09/28cd7265-afc9-4084-81b2-3b67cfd6383a-1.jpg</thumbnail>
<fanart>https://esportenewsmundo.com.br/wp-content/uploads/2022/09/28cd7265-afc9-4084-81b2-3b67cfd6383a-1.jpg</fanart>
<info>Confira a transmissão em tempo real do Esporte News Mundo do jogo entre América-MG x São Paulo pela Copa do Brasil. O pré-jogo começa às 19h30 e o jogo às 21h00.</info>
</item>

<item>
<title>[B]São Paulo [COLOR gold]x[/COLOR] Atlético-GO HD[/B]</title>
<link> </link>
<thumbnail>https://esportenewsmundo.com.br/wp-content/uploads/2022/09/28cd7265-afc9-4084-81b2-3b67cfd6383a-1.jpg</thumbnail>
<fanart>https://esportenewsmundo.com.br/wp-content/uploads/2022/09/28cd7265-afc9-4084-81b2-3b67cfd6383a-1.jpg</fanart>
<info>Confira a transmissão em tempo real do Esporte News Mundo do jogo entre América-MG x São Paulo pela Copa do Brasil. O pré-jogo começa às 19h30 e o jogo às 21h00.</info>
</item>

